simplydomain/__init__.py
simplydomain/config.py
simplydomain/bin/simply_domain.py
simplydomain/src/__init__.py
simplydomain/src/core_logger.py
simplydomain/src/core_output.py
simplydomain/src/core_printer.py
simplydomain/src/core_processes.py
simplydomain/src/core_progress.py
simplydomain/src/core_runtime.py
simplydomain/src/core_scrub.py
simplydomain/src/core_serialization.py
simplydomain/src/module_checker.py
simplydomain/src/module_helpers.py
simplydomain/src/module_loader.py
simplydomain/src/module_multiprocessing.py
simplydomain/src/module_provider.py
simplydomain/src/module_recursion.py
simplydomain/src/module_resolvers.py
simplydomain/src/dynamic_modules/__init__.py
simplydomain/src/dynamic_modules/bing_search.py
simplydomain/src/dynamic_modules/crtsh_search.py
simplydomain/src/dynamic_modules/dnsdumpster_search.py
simplydomain/src/dynamic_modules/module_template.py
simplydomain/src/dynamic_modules/virustotal_search.py
simplydomain/src/static_modules/__init__.py
simplydomain/src/static_modules/subdomain_bruteforce.py
simplydomain/src/static_modules/subdomain_raw_bruteforce.py
simplydomain/tests/__init__.py
simplydomain/tests/test_corePrinters.py
simplydomain/tests/test_dnsServers.py
simplydomain/tests/test_requestsHelpers.py
simplydomain-2.0.9.data/scripts/simply_domain.py
simplydomain-2.0.9.dist-info/LICENSE
simplydomain-2.0.9.dist-info/METADATA
simplydomain-2.0.9.dist-info/WHEEL
simplydomain-2.0.9.dist-info/top_level.txt
simplydomain-2.0.9.dist-info/RECORD
