Metadata-Version: 2.1
Name: simplydomain
Version: 2.0.9
Summary: simplydomain is a very basic framework to automate domain brute forcing.
Home-page: http://github.com/SimplySecurity/simplydomain-pkg
Author: Alexander Rymdeko-Harvey
Author-email: a.rymdekoharvey@obscuritylabs.com
License: BSD 3.0
Platform: UNKNOWN
Classifier: Development Status :: 4 - Beta
Classifier: Programming Language :: Python :: 3.6
Classifier: Programming Language :: Python :: 3.7
Requires-Dist: aiodns
Requires-Dist: aiohttp
Requires-Dist: beautifulsoup4
Requires-Dist: crtsh
Requires-Dist: dnsdumpster
Requires-Dist: fake-useragent
Requires-Dist: json2xml
Requires-Dist: requests
Requires-Dist: setuptools
Requires-Dist: termcolor
Requires-Dist: tqdm
Requires-Dist: uvloop
Requires-Dist: validators
Requires-Dist: click
